[{"date":"","description":"30 Violinos comprados de Kleber","brl":40000,"usd":0},{"date":"","description":"1 Violinos comprados de Kleber","brl":1333,"usd":0},{"date":"","description":"Envio Sam Ash 5 un violinos NY","brl":1670.99,"usd":0},{"date":"","description":"Segundo envio 6 un","brl":1309.49,"usd":0},{"date":"","description":"Terceiro envio 7 un","brl":2117.37,"usd":0},{"date":"","description":"Frete 6 violinos para Isaac","brl":1210,"usd":0},{"date":"","description":"Pedro Bronka, Logo + Catálogo","brl":0,"usd":0},{"date":"","description":"+ teste R$ 100 Printi","brl":2100,"usd":0},{"date":"12/13/2018","description":"Bronka shopify 1/2","brl":1500,"usd":0},{"date":"4/26/2019","description":"Bronka shopify 2/2","brl":1500,"usd":0},{"date":"","description":"Dominio auroraviolins.com","brl":62.2,"usd":15.17},{"date":"4/17/2019","description":"Registered Agents of Florida","brl":200.9,"usd":49},{"date":"4/17/2019","description":"Sunbiz Reinstatement","brl":2685.5,"usd":655},{"date":"","description":"Facebook Ads","brl":0,"usd":0},{"date":"4/12/2019","description":"PAYPAL -FACEBOOKSER","brl":50.62,"usd":0},{"date":"4/30/2019","description":"Ccard FACEBK LMXP3LWBG2","brl":122.78,"usd":0},{"date":"5/25/2019","description":"FACEBK 8MZFVLECG2","brl":200,"usd":0},{"date":"5/31/2019","description":"FACEBK P6GAEMSCG2","brl":47.97,"usd":0},{"date":"6/23/2019","description":"FACEBK AN87RMSCG2","brl":200,"usd":0},{"date":"6/30/2019","description":"FACEBK SUJ3VMSCG2","brl":49.78,"usd":0},{"date":"7/21/2019","description":"Facebook V5Q9FN6CG2","brl":200,"usd":0},{"date":"7/31/2019","description":"Facebook LF5KCMACG2","brl":83.58,"usd":0},{"date":"8/30/2019","description":"Facebook MQMDWMWBG2","brl":200,"usd":0},{"date":"8/31/2019","description":"Facebook 8TUV3P6CG2","brl":14.1,"usd":0},{"date":"9/30/2019","description":"Facebook KDTMANNCG2","brl":189.79,"usd":0},{"date":"10/31/2019","description":"Facebook TT9UUNNCG2","brl":170.64,"usd":0},{"date":"11/25/2019","description":"Facebook RXKQWPECG2","brl":200,"usd":0},{"date":"","description":"Shopify","brl":0,"usd":0},{"date":"11/21/2018","description":"SHOPIFY * 57095736","brl":118.9,"usd":29},{"date":"12/22/2018","description":"SHOPIFY * 58186937","brl":118.9,"usd":29},{"date":"1/21/2019","description":"SHOPIFY * 59236837","brl":118.9,"usd":29},{"date":"2/20/2019","description":"SHOPIFY * 60356127","brl":118.9,"usd":29},{"date":"3/22/2019","description":"SHOPIFY * 61528881","brl":118.9,"usd":29},{"date":"4/21/2019","description":"SHOPIFY * 62719516","brl":118.9,"usd":29},{"date":"5/21/2019","description":"SHOPIFY * 63930615","brl":118.9,"usd":29},{"date":"6/24/2019","description":"SHOPIFY * 65157889","brl":118.9,"usd":29},{"date":"7/23/2019","description":"SHOPIFY * 66393472","brl":118.9,"usd":29},{"date":"8/21/2019","description":"SHOPIFY * 67617824","brl":118.9,"usd":29},{"date":"9/20/2019","description":"SHOPIFY.COM/C 8887467439","brl":118.9,"usd":29},{"date":"10/22/2019","description":"SHOPIFY.COM/C 8887467439","brl":118.9,"usd":29},{"date":"11/19/2019","description":"SHOPIFY.COM/C 8887467439","brl":118.9,"usd":29},{"date":"","description":"Citibank","brl":0,"usd":0},{"date":"11/1/2018","description":"Monthly Service Fee","brl":102.5,"usd":25},{"date":"12/3/2019","description":"Monthly Service Fee","brl":102.5,"usd":25},{"date":"1/2/2019","description":"Monthly Service Fee","brl":102.5,"usd":25},{"date":"2/1/2019","description":"Monthly Service Fee","brl":102.5,"usd":25},{"date":"3/1/2019","description":"Monthly Service Fee","brl":102.5,"usd":25},{"date":"4/1/2019","description":"Monthly Service Fee","brl":102.5,"usd":25},{"date":"5/1/2019","description":"Monthly Service Fee","brl":102.5,"usd":25},{"date":"6/3/2019","description":"Monthly Service Fee","brl":102.5,"usd":25},{"date":"7/1/2019","description":"Monthly Service Fee","brl":102.5,"usd":25},{"date":"7/17/2019","description":"Transferwise Fee","brl":368.67,"usd":89.92},{"date":"8/8/2019","description":"Transferwise Fee","brl":248.83,"usd":60.69},{"date":"8/1/2019","description":"Monthly Service Fee","brl":102.5,"usd":25},{"date":"9/3/2019","description":"Monthly Service Fee","brl":102.5,"usd":25},{"date":"10/1/2019","description":"Monthly Service Fee","brl":102.5,"usd":25},{"date":"11/1/2019","description":"Monthly Service Fee","brl":102.5,"usd":25},{"date":"","description":"Phase 2","brl":0,"usd":0},{"date":"6/25/2019","description":"10 violinos + 2 cellos 1/5","brl":4107.84,"usd":1056},{"date":"9/19/2019","description":"Compra violino branco","brl":2070,"usd":0},{"date":"9/23/2019","description":"reparos e envios","brl":493,"usd":0},{"date":"","description":"taxas","brl":16.59,"usd":0},{"date":"9/27/2019","description":"Fotos 2020","brl":1600,"usd":0},{"date":"10/17/2019","description":"Bronka 1/2","brl":2200,"usd":0},{"date":"","description":"classic preto 5 cordas","brl":2070,"usd":0},{"date":"11/5/2019","description":"10 violinos + 2 cellos 2/5","brl":4107.84,"usd":1056},{"date":"11/12/2019","description":"6 violinos 6 cordas 1/5","brl":2312,"usd":0},{"date":"11/29/2019","description":"6 v 6c +1v 6c + 3v6c 2/5","brl":5148,"usd":0},{"date":"12/17/2019","description":"Classic branco 5c selena e frete","brl":2230,"usd":0},{"date":"12/17/2019","description":"Parcela unificada 3/6","brl":6738.38,"usd":0},{"date":"1/31/2020","description":"Aurora Classic 4 str white","brl":1512,"usd":0},{"date":"2/4/2020","description":"Parcela unificada 4/6","brl":6738.38,"usd":0},{"date":"2/15/2020","description":"Parcela unificada 5/6","brl":6738.38,"usd":0},{"date":"3/17/2020","description":"Parcela unificada 6/6","brl":6738.38,"usd":0},{"date":"","description":"Investido","brl":108996.82,"usd":142161.69}]
